core/__init__.py
core/foodweb.py
core/organism.py
core/terrain.py
ecosim2d-0.1.2.dist-info/licenses/LICENSE
logic/__init__.py
logic/behavior.py
logic/reproduction.py
mainsimulation/__init__.py
mainsimulation/main.py
simulation/__init__.py
simulation/engine.py
statistic_tools/__init__.py
statistic_tools/heatmap.py
statistic_tools/population.py
visualizer/__init__.py
visualizer/plot.py
ecosim2d-0.1.2.dist-info/METADATA
ecosim2d-0.1.2.dist-info/WHEEL
ecosim2d-0.1.2.dist-info/top_level.txt
ecosim2d-0.1.2.dist-info/RECORD
