Metadata-Version: 2.4
Name: ecosim2d
Version: 0.1.2
Summary: Ecosystem simulation toolbox in Python
Author: Anna Schleier, Anikó Vitos, Tamás Bence Tóth
Project-URL: Homepage, https://github.com/schan45/ecosim
Project-URL: Documentation, https://ecosim.readthedocs.io/
Requires-Python: >=3.8
License-File: LICENSE
Requires-Dist: numpy
Requires-Dist: matplotlib
Requires-Dist: imageio
Requires-Dist: Pillow
Requires-Dist: scipy
Requires-Dist: seaborn
Dynamic: license-file
